mab_algo/__init__.py
mab_algo/algorithms/__init__.py
mab_algo/algorithms/algorithm.py
mab_algo/algorithms/epsilon_greedy.py
mab_algo/algorithms/gradient_bandit.py
mab_algo/algorithms/ucb.py
mab_algo/averages/__init__.py
mab_algo/averages/average.py
mab_algo/averages/exp_moving_avg.py
mab_algo/averages/simple_avg.py
mab_algo/averages/weighted_avg.py
tests/__init__.py
tests/algorithms/__init__.py
tests/algorithms/test_algorithms.py
tests/algorithms/test_epsilon_greedy.py
tests/algorithms/test_gradient_bandit.py
tests/algorithms/test_ucb.py
tests/averages/__init__.py
tests/averages/test_exp_moving_avg.py
tests/averages/test_simple_avg.py
tests/averages/test_weighted_avg.py
mab_algo-1.0.0.dist-info/LICENSE
mab_algo-1.0.0.dist-info/METADATA
mab_algo-1.0.0.dist-info/WHEEL
mab_algo-1.0.0.dist-info/top_level.txt
mab_algo-1.0.0.dist-info/RECORD
