Metadata-Version: 2.1
Name: mab_algo
Version: 1.0.0
Summary: Implementation of Multi Armed Bandit algorithms from "Reinforcement Learning - An Introduction" by Richard S. Sutton and Andrew G. Barto
Home-page: https://github.com/LavishKK2022/mab_algo
Author: Lavish Kamal Kumar
Author-email: dev@lavish-kumar.com
License-File: LICENSE
